hueText/__init__.py
huetext-0.0.1.dist-info/METADATA
huetext-0.0.1.dist-info/WHEEL
huetext-0.0.1.dist-info/licenses/LICENCE.txt
huetext-0.0.1.dist-info/RECORD
