Metadata-Version: 2.1
Name: hueText
Version: 0.0.1
Summary: This is an easy to use Python library which allows you to make your terminal outputs more colorful and therefore easier to read and understand 
Project-URL: Homepage, https://github.com/mubashir6u/hueText
Project-URL: Bug Tracker, https://github.com/mubashir6u/hueText/issues
Author-email: "Engr. Mubashir Hussain" <mubashir6u@gmail.com>
License-File: LICENCE.txt
Classifier: License :: OSI Approved :: GNU General Public License v3 (GPLv3)
Classifier: Operating System :: OS Independent
Classifier: Programming Language :: Python :: 3
Requires-Python: >=3.7
